easyplot/__init__.py
easyplot/cant_use_.py
easyplot/fix_bug_.py
easyplot/sandbox1_.py
easyplot_tool-0.1.0.dist-info/METADATA
easyplot_tool-0.1.0.dist-info/WHEEL
easyplot_tool-0.1.0.dist-info/top_level.txt
easyplot_tool-0.1.0.dist-info/RECORD
